<repast.simphony.data.engine.DefaultDataGathererDescriptor>
  <name>MarketDataSet</name>
  <dataSetId class="string">MarketDataSet</dataSetId>
  <scheduleParameters>
    <start>1.0</start>
    <interval>1.0</interval>
    <priority>-Infinity</priority>
    <duration>-1.0</duration>
    <frequency>REPEAT</frequency>
  </scheduleParameters>
  <dataMappingContainer class="repast.simphony.data.logging.gather.DefaultDataMappingContainer">
    <nameMappingTable>
      <entry>
        <string>AverageDemand</string>
        <repast.simphony.data.logging.gather.MethodMapping>
          <method>
            <class>uk.ac.cranfield.cascade.market.Market</class>
            <name>getAverageDemand</name>
            <parameter-types/>
          </method>
        </repast.simphony.data.logging.gather.MethodMapping>
      </entry>
      <entry>
        <string>Tick</string>
        <repast.simphony.data.logging.gather.DefaultTimeDataMapping/>
      </entry>
      <entry>
        <string>Mapping0</string>
        <repast.simphony.data.logging.BSFMapping>
          <bsfExpression>value = agent.getAverageDemand() / 20;</bsfExpression>
          <bsfLanguage>beanshell</bsfLanguage>
        </repast.simphony.data.logging.BSFMapping>
      </entry>
      <entry>
        <string>s2</string>
        <repast.simphony.data.logging.gather.MethodMapping>
          <method>
            <class>uk.ac.cranfield.cascade.market.Market</class>
            <name>s2</name>
            <parameter-types/>
          </method>
        </repast.simphony.data.logging.gather.MethodMapping>
      </entry>
      <entry>
        <string>s1</string>
        <repast.simphony.data.logging.gather.MethodMapping>
          <method>
            <class>uk.ac.cranfield.cascade.market.Market</class>
            <name>s1</name>
            <parameter-types/>
          </method>
        </repast.simphony.data.logging.gather.MethodMapping>
      </entry>
      <entry>
        <string>AverageCost</string>
        <repast.simphony.data.logging.gather.MethodMapping>
          <method>
            <class>uk.ac.cranfield.cascade.market.Market</class>
            <name>getAverageCost</name>
            <parameter-types/>
          </method>
        </repast.simphony.data.logging.gather.MethodMapping>
      </entry>
    </nameMappingTable>
    <mappingNameTable>
      <entry>
        <repast.simphony.data.logging.gather.MethodMapping reference="../../../nameMappingTable/entry[4]/repast.simphony.data.logging.gather.MethodMapping"/>
        <string>s2</string>
      </entry>
      <entry>
        <repast.simphony.data.logging.gather.MethodMapping reference="../../../nameMappingTable/entry/repast.simphony.data.logging.gather.MethodMapping"/>
        <string>AverageDemand</string>
      </entry>
      <entry>
        <repast.simphony.data.logging.gather.DefaultTimeDataMapping reference="../../../nameMappingTable/entry[2]/repast.simphony.data.logging.gather.DefaultTimeDataMapping"/>
        <string>Tick</string>
      </entry>
      <entry>
        <repast.simphony.data.logging.gather.MethodMapping reference="../../../nameMappingTable/entry[5]/repast.simphony.data.logging.gather.MethodMapping"/>
        <string>s1</string>
      </entry>
      <entry>
        <repast.simphony.data.logging.gather.MethodMapping reference="../../../nameMappingTable/entry[6]/repast.simphony.data.logging.gather.MethodMapping"/>
        <string>AverageCost</string>
      </entry>
      <entry>
        <repast.simphony.data.logging.BSFMapping reference="../../../nameMappingTable/entry[3]/repast.simphony.data.logging.BSFMapping"/>
        <string>Mapping0</string>
      </entry>
    </mappingNameTable>
  </dataMappingContainer>
  <aggregateContainer class="repast.simphony.data.logging.gather.DefaultAggregateDataMappingContainer">
    <nameMappingTable/>
    <mappingNameTable/>
    <alternatedNameTable/>
    <nameAlternatedTable/>
  </aggregateContainer>
  <agentClass>uk.ac.cranfield.cascade.market.Market</agentClass>
</repast.simphony.data.engine.DefaultDataGathererDescriptor>